README.md
setup.py
tech_company/__init__.py
tech_company/cloud.py
tech_company.egg-info/PKG-INFO
tech_company.egg-info/SOURCES.txt
tech_company.egg-info/dependency_links.txt
tech_company.egg-info/top_level.txt
tech_company/example/__init__.py
tech_company/example/example.py