Metadata-Version: 2.1
Name: tech-company
Version: 0.0.2
Summary: A Tech Company
Home-page: https://example.org
Author: T Smith
Author-email: dev@null.org
License: UNKNOWN
Platform: UNKNOWN
Classifier: Programming Language :: Python :: 3
Classifier: License :: OSI Approved :: MIT License
Classifier: Operating System :: OS Independent
